{
  "version": 2,
  "extractor": "pdffigures2",
  "figures": [
    {
      "url": "assets/figures/arxiv/2604.11096v1/fig-001.webp",
      "caption": "Table 3: Statistics of CSLM’s continuing pre-training data.",
      "page": 6,
      "index": 1,
      "width": 463,
      "height": 317
    },
    {
      "url": "assets/figures/arxiv/2604.11096v1/fig-002.webp",
      "caption": "Table 2: Results of Chinese ASR and TTS tasks. The test datasets include AISHELL-1 (Bu et al., 2017), AISHELL-2 (Du et al., 2018) and AISHELL-3 (Shi et al., 2021). The last column “GT” represents the error rates of the original speech-text pairs from the dataset calculated using the paraformer large model.",
      "page": 6,
      "index": 2,
      "width": 771,
      "height": 207
    },
    {
      "url": "assets/figures/arxiv/2604.11096v1/fig-003.webp",
      "caption": "Figure 2: Model architecture and inference process of CSLM.",
      "page": 4,
      "index": 3,
      "width": 948,
      "height": 373
    },
    {
      "url": "assets/figures/arxiv/2604.11096v1/fig-004.webp",
      "caption": "Table 10: Impact of chain-of-modality forms on speechto-speech conversations.",
      "page": 9,
      "index": 4,
      "width": 456,
      "height": 519
    }
  ]
}